LICENSE
README.md
setup.py
ace_step.egg-info/PKG-INFO
ace_step.egg-info/SOURCES.txt
ace_step.egg-info/dependency_links.txt
ace_step.egg-info/entry_points.txt
ace_step.egg-info/requires.txt
ace_step.egg-info/top_level.txt
acestep/__init__.py
acestep/apg_guidance.py
acestep/data_sampler.py
acestep/gui.py
acestep/pipeline_ace_step.py
acestep/text2music_dataset.py