Metadata-Version: 2.4
Name: ace_step
Version: 0.1.0
Summary: ACE Step: A Step Towards Music Generation Foundation Model
Author: ACE Studio, StepFun AI
License: Apache 2.0
Classifier: Development Status :: 3 - Alpha
Classifier: Intended Audience :: Science/Research
Classifier: License :: OSI Approved :: Apache Software License
License-File: LICENSE
Requires-Dist: datasets==3.4.1
Requires-Dist: diffusers==0.32.2
Requires-Dist: gradio==5.23.3
Requires-Dist: librosa==0.11.0
Requires-Dist: loguru==0.7.3
Requires-Dist: matplotlib==3.10.1
Requires-Dist: numpy
Requires-Dist: pypinyin==0.53.0
Requires-Dist: pytorch_lightning==2.5.1
Requires-Dist: soundfile==0.13.1
Requires-Dist: torch
Requires-Dist: torchaudio
Requires-Dist: torchvision
Requires-Dist: tqdm==4.67.1
Requires-Dist: transformers==4.50.0
Requires-Dist: py3langid==0.3.0
Requires-Dist: hangul-romanize==0.1.0
Requires-Dist: num2words==0.5.14
Requires-Dist: spacy==3.8.4
Requires-Dist: accelerate==1.6.0
Requires-Dist: cutlet
Requires-Dist: fugashi[unidic-lite]
Requires-Dist: click
Dynamic: author
Dynamic: classifier
Dynamic: description
Dynamic: description-content-type
Dynamic: license
Dynamic: license-file
Dynamic: requires-dist
Dynamic: summary
